{"pageid": 1077219, "title": "পেলোড (কম্পিউটিং)", "url": "https://bn.wikipedia.org/wiki?curid=1077219", "content": "কম্পিউটিং এবং টেলিযোগাযোগে, পেলোড হলো প্রেরিত তথ্যের অংশ যা প্রকৃত উদ্দেশ্য বার্তা। হেডার এবং মেটাডেটা পাঠানো হয় শুধুমাত্র পেলোড ডেলিভারি সক্ষম করতে।\nএকটি কম্পিউটার ভাইরাস বা ওয়ার্ম প্রেক্ষাপটে, পেলোড হলো ম্যালওয়্যারের অংশ যা দূষিত কাজ করে।\nশব্দটি পরিবহন থেকে আনা হয়েছে, যেখানে পেলোড বোঝায় বোঝার অংশ যা পরিবহনের জন্য অর্থ প্রদান করে।\n\n\n== নেটওয়ার্কিং ==\nকম্পিউটার নেটওয়ার্কে, প্রেরিত ডেটা হলো পেলোড। এটি প্রায় সবসময়ই কোন না কোন ধরনের ফ্রেম বিন্যাসে আবৃত থাকে, যা ফ্রেমিং বিট এবং ফ্রেম চেক ক্রম দ্বারা গঠিত। উদাহরণস্বরূপ: ইথারনেট ফ্রেম, পয়েন্ট টু পয়েন্ট প্রোটোকল (পিপিপি) ফ্রেম, ফাইবার চ্যানেল ফ্রেম এবং ভি.৪২ মডেম ফ্রেম।\n\n\n== প্রোগ্রামিং ==\nকম্পিউটার প্রোগ্রামিংয়ে, শব্দটির সবচেয়ে সাধারণ ব্যবহার হলো বার্তা প্রোটোকলের প্রেক্ষাপটে, প্রকৃত তথ্য থেকে প্রোটোকল ওভারহেডকে আলাদা করতে। উদাহরণস্বরূপ, একটি জেএসওএন ওয়েব সার্ভিস প্রতিক্রিয়া হতে পারে:\n\n{ \"data\": { \"message\": \"Hello, world!\" } }\n\nস্ট্রিং Hello, world! জেএসওএন বার্তার পেলোড, বাকিটা প্রোটোকল ওভারহেড।\n\n\n== নিরাপত্তা ==\nকম্পিউটার সুরক্ষায়, পেলোড হলো ব্যক্তিগত ব্যবহারকারীর পাঠ্যের অংশ যার মধ্যে ম্যালওয়্যার যেমন ভাইরাস বা ওয়ার্ম থাকতে পারে যা দূষিত কাজ করে; ডেটা মুছে ফেলা, স্প্যাম পাঠানো বা ডেটা এনক্রিপ্ট করা। পেলোড ছাড়াও, এই ধরনের ম্যালওয়্যারে সাধারণত ওভারহেড কোড থাকে যার লক্ষ্য কেবল নিজেকে ছড়িয়ে দেওয়া, বা সনাক্তকরণ এড়ানো।\n\n\n== তথ্যসূত্র =="}